doomiapi/__init__.py
doomiapi/asr.py
DoomiPyApi-1.0.0.dist-info/METADATA
DoomiPyApi-1.0.0.dist-info/WHEEL
DoomiPyApi-1.0.0.dist-info/top_level.txt
DoomiPyApi-1.0.0.dist-info/RECORD
